pyminhash/__init__.py
pyminhash/datasets.py
pyminhash/pyminhash.py
pyminhash/data/stoxx50_extended_with_id.xlsx
PyMinHash-0.1.5.dist-info/LICENSE
PyMinHash-0.1.5.dist-info/METADATA
PyMinHash-0.1.5.dist-info/WHEEL
PyMinHash-0.1.5.dist-info/top_level.txt
PyMinHash-0.1.5.dist-info/RECORD
