Metadata-Version: 2.1
Name: PyMinHash
Version: 0.1.5
Summary: Efficient MinHashing
Home-page: https://github.com/fritshermans/pyminhash
Author: Frits Hermans
Classifier: Programming Language :: Python :: 3
Classifier: License :: OSI Approved :: MIT License
Classifier: Operating System :: OS Independent
Requires-Python: >=3.6.9
License-File: LICENSE
Requires-Dist: pandas
Requires-Dist: numpy
Requires-Dist: scikit-learn
Requires-Dist: pytest
Requires-Dist: openpyxl
Provides-Extra: base
Requires-Dist: pandas ; extra == 'base'
Requires-Dist: numpy ; extra == 'base'
Requires-Dist: scikit-learn ; extra == 'base'
Requires-Dist: pytest ; extra == 'base'
Requires-Dist: openpyxl ; extra == 'base'
Provides-Extra: dev
Requires-Dist: pandas ; extra == 'dev'
Requires-Dist: numpy ; extra == 'dev'
Requires-Dist: scikit-learn ; extra == 'dev'
Requires-Dist: pytest ; extra == 'dev'
Requires-Dist: openpyxl ; extra == 'dev'
Requires-Dist: jupyterlab ; extra == 'dev'
Requires-Dist: sphinx (==3.5.4) ; extra == 'dev'
Requires-Dist: nbsphinx ; extra == 'dev'
Requires-Dist: sphinx-rtd-theme ; extra == 'dev'
Provides-Extra: docs
Requires-Dist: sphinx (==3.5.4) ; extra == 'docs'
Requires-Dist: nbsphinx ; extra == 'docs'
Requires-Dist: sphinx-rtd-theme ; extra == 'docs'
